LICENSE
MANIFEST.in
README.md
pyproject.toml
requirements.txt
setup.cfg
setup.py
tfswin/__init__.py
tfswin/basic.py
tfswin/drop.py
tfswin/embed.py
tfswin/merge.py
tfswin/mlp.py
tfswin/model.py
tfswin/swin.py
tfswin/winatt.py
tfswin/window.py
tfswin.egg-info/PKG-INFO
tfswin.egg-info/SOURCES.txt
tfswin.egg-info/dependency_links.txt
tfswin.egg-info/requires.txt
tfswin.egg-info/top_level.txt