Metadata-Version: 2.1
Name: tfswin
Version: 4.1.1
Summary: keras.src (TensorFlow v2) reimplementation of Swin Transformer V1 & V2 models.
Home-page: https://github.com/shkarupa-alex/tfswin
Author: Shkarupa Alex
Author-email: shkarupa.alex@gmail.com
License: MIT
Platform: UNKNOWN
Classifier: Development Status :: 5 - Production/Stable
Classifier: Intended Audience :: Developers
Classifier: Intended Audience :: Education
Classifier: Intended Audience :: Science/Research
Classifier: License :: OSI Approved :: MIT License
Classifier: Programming Language :: Python :: 3
Classifier: Topic :: Scientific/Engineering
Classifier: Topic :: Software Development
Classifier: Topic :: Software Development :: Libraries
Classifier: Topic :: Software Development :: Libraries :: Python Modules
License-File: LICENSE
